README
setup.cfg
setup.py
report/__init__.py
report/config.py
report/console.py
report/util.py
report/version.py
reporting.egg-info/PKG-INFO
reporting.egg-info/SOURCES.txt
reporting.egg-info/dependency_links.txt
reporting.egg-info/requires.txt
reporting.egg-info/top_level.txt