Metadata-Version: 1.1
Name: reporting
Version: 0.33
Summary: Reporting is better than printing
Home-page: https://github.com/mattvonrocketstein/reporting/
Author: mattvonrocketstein
Author-email: $author@gmail
License: UNKNOWN
Download-URL: https://github.com/mattvonrocketstein/reporting//tarball/master
Keywords: report
Platform: UNKNOWN
